<?xml version="1.0" encoding="UTF-8"?><record_update>
    <sys_choice action="DELETE" field="u_request_type" table="x_58872_needit_needit" version="3">
        <sys_choice_set action="DELETE">
            <element>u_request_type</element>
            <name>x_58872_needit_needit</name>
            <sys_class_name/>
            <sys_created_by/>
            <sys_created_on/>
            <sys_id/>
            <sys_mod_count/>
            <sys_name/>
            <sys_package/>
            <sys_policy/>
            <sys_scope/>
            <sys_update_name/>
            <sys_updated_by/>
            <sys_updated_on>2020-06-25 19:41:43</sys_updated_on>
        </sys_choice_set>
    </sys_choice>
    <sys_update_version action="INSERT_OR_UPDATE">
        <action>DELETE</action>
        <application/>
        <file_path/>
        <instance_id>97bf3d7cdb6304949df22f17d4961995</instance_id>
        <instance_name>dev102937</instance_name>
        <name>sys_choice_x_58872_needit_needit_u_request_type</name>
        <payload><![CDATA[<?xml version="1.0" encoding="UTF-8"?><record_update><sys_choice action="DELETE" field="u_request_type" table="x_58872_needit_needit" version="3"><sys_choice_set action="DELETE"><element>u_request_type</element><name>x_58872_needit_needit</name><sys_class_name/><sys_created_by/><sys_created_on/><sys_id/><sys_mod_count/><sys_name/><sys_package/><sys_policy/><sys_scope/><sys_update_name/><sys_updated_by/><sys_updated_on>2020-06-25 19:41:43</sys_updated_on></sys_choice_set></sys_choice></record_update>]]></payload>
        <payload_hash>1828161538</payload_hash>
        <record_name>x_58872_needit_needit.u_request_type</record_name>
        <reverted_from/>
        <source>2518c23e2f259010b78adcb6f699b68a</source>
        <source_table>sys_update_set</source_table>
        <state>previous</state>
        <sys_created_by>admin</sys_created_by>
        <sys_created_on>2020-06-25 19:41:43</sys_created_on>
        <sys_id>d218063e2f259010b78adcb6f699b64a</sys_id>
        <sys_mod_count>0</sys_mod_count>
        <sys_recorded_at>172ed000dc20000001</sys_recorded_at>
        <sys_updated_by>admin</sys_updated_by>
        <sys_updated_on>2020-06-25 19:41:43</sys_updated_on>
        <type>Choice list</type>
        <update_guid>5e18063ea825901031405feb73e1ee49</update_guid>
        <update_guid_history>5e18063ea825901031405feb73e1ee49:1828161538,1a18063efb25901031287219d92bb346:1429053012,9618063e62259010da36130b84920d43:-1514400100,e4ec357602259010aaf049b5f92c091c:0,80dcfd365a259010ada1227f26c6c2ff:-717865848,04dcfd36b3259010d31a0d140c5a13fb:-1701966180,80dcfd36ae259010c54c9fd85666d0f8:736548692,00dcfd36ee25901038c4a79f64805ef5:833312879,eeedc9f6caa19010d534af895436dbfe:0,e3dd49f69da19010bbc09ab2d8630313:1927160066,67dd49f669a19010a4f5cc1d7f94480f:-1701966180,e3dd49f616a19010eb0b8bf4011c8b0c:736548692,63dd49f63aa1901073ac0426895aad09:833312879,b871d9266c695010401e6e1baca7e8dc:0,5a61592633695010807da28b6ef90764:-1161396533,da6159262569501092c3eb803ab61660:-1701966180,5a61592609695010210a25c0f9dc0d5d:736548692,d6615926e06950107ceed37bf186ef5a:833312879,e274b8a2b1295010e3b737a5253ad408:0,ee7478a2672950107ad03ed017e3c4e0:833312879</update_guid_history>
    </sys_update_version>
    <sys_metadata_delete action="INSERT_OR_UPDATE">
        <sys_audit_delete/>
        <sys_class_name>sys_metadata_delete</sys_class_name>
        <sys_created_by>admin</sys_created_by>
        <sys_created_on>2020-06-25 19:41:57</sys_created_on>
        <sys_db_object display_value="" name="sys_choice_set">sys_choice_set</sys_db_object>
        <sys_id>2528863e2f259010b78adcb6f699b6d6</sys_id>
        <sys_metadata>2528863e2f259010b78adcb6f699b6d6</sys_metadata>
        <sys_mod_count>0</sys_mod_count>
        <sys_name>u_request_type</sys_name>
        <sys_package display_value="NeedIt" source="x_58872_needit">6ead8e780f603200cd674f8ce1050ed1</sys_package>
        <sys_parent/>
        <sys_policy/>
        <sys_scope display_value="NeedIt">6ead8e780f603200cd674f8ce1050ed1</sys_scope>
        <sys_scope_delete display_value="">94872a8897db403e8ee69a431de2fca4</sys_scope_delete>
        <sys_update_name>sys_choice_x_58872_needit_needit_u_request_type</sys_update_name>
        <sys_update_version display_value="sys_choice_x_58872_needit_needit_u_request_type">d218063e2f259010b78adcb6f699b64a</sys_update_version>
        <sys_updated_by>admin</sys_updated_by>
        <sys_updated_on>2020-06-25 19:41:57</sys_updated_on>
    </sys_metadata_delete>
</record_update>
